{
    "defaultSeverity": "error",
    "extends": [
        "tslint:recommended"
    ],
    "jsRules": {
    },
    "rules": {
        "interface-name": false,
        "only-arrow-functions": false,
        "no-shadowed-variable": false,
        "quotemark": [true, "single" ],
        "interface-over-type-literal": false,
        "member-ordering": [
            true,
            {
              "order": [
                "public-instance-field",
                "private-instance-field",
                "public-static-field",
                "private-static-field",
                "public-constructor",
                "private-constructor",
                "public-instance-method",
                "protected-instance-method",
                "private-instance-method"
              ],
              "alphabetize": true
            }
          ],
        "max-line-length": [true, 250]
    },
    "rulesDirectory": []
}